[
  {
    "name": "Bar do Chucrutes",
    "description": "picapau",
    "image": "https://api.adorable.io/avatars/285/abott@adorable.png"
  },
  {
    "name": "Rafinhas",
    "description": "chaves",
    "image": "https://api.adorable.io/avatars/285/abott@adorable.png"
  },
  {
    "name": "Samuquinha",
    "description": "samurai",
    "image": "https://api.adorable.io/avatars/285/abott@adorable.png"
  },
  {
    "name": "Fêzinho",
    "description": "pensando no frango",
    "image": "https://api.adorable.io/avatars/285/abott@adorable.png"
  },
  {
    "name": "Charleston",
    "description": "10",
    "image": "https://api.adorable.io/avatars/285/abott@adorable.png"
  }
]
